odoo9_addon_l10n_fr_department_oversea-9.0.1.0.0.99.dev3-py2.7-nspkg.pth
odoo9_addon_l10n_fr_department_oversea-9.0.1.0.0.99.dev3.dist-info/METADATA
odoo9_addon_l10n_fr_department_oversea-9.0.1.0.0.99.dev3.dist-info/RECORD
odoo9_addon_l10n_fr_department_oversea-9.0.1.0.0.99.dev3.dist-info/WHEEL
odoo9_addon_l10n_fr_department_oversea-9.0.1.0.0.99.dev3.dist-info/namespace_packages.txt
odoo9_addon_l10n_fr_department_oversea-9.0.1.0.0.99.dev3.dist-info/top_level.txt
odoo_addons/l10n_fr_department_oversea/README.rst
odoo_addons/l10n_fr_department_oversea/__init__.py
odoo_addons/l10n_fr_department_oversea/__openerp__.py
odoo_addons/l10n_fr_department_oversea/post_install.py
odoo_addons/l10n_fr_department_oversea/data/res_country_department.xml
odoo_addons/l10n_fr_department_oversea/data/res_country_state.xml
odoo_addons/l10n_fr_department_oversea/static/description/icon.png
odoo_addons/l10n_fr_department_oversea/tests/__init__.py
odoo_addons/l10n_fr_department_oversea/tests/test_department_oversea.py
