Metadata-Version: 2.1
Name: odoo9-addon-l10n-fr-department-oversea
Version: 9.0.1.0.0.99.dev3
Summary: Populate Database with overseas French Departments (Départements d'outre-mer)
Home-page: http://www.akretion.com
Author: Akretion,Odoo Community Association (OCA)
Author-email: support@odoo-community.org
License: AGPL-3
Platform: UNKNOWN
Classifier: Programming Language :: Python
Classifier: Framework :: Odoo
Classifier: License :: OSI Approved :: GNU Affero General Public License v3
Requires-Python: ~=2.7
Requires-Dist: odoo9-addon-l10n-fr-department
Requires-Dist: odoo (<9.1a,>=9.0a)
